pdtj/__init__.py
pdtj/__version__.py
pdtj/constants.py
pdtj/docstring_handler.py
pdtj/files_finder.py
pdtj/json_generator.py
pdtj/parameters.py
pdtj/util.py
pdtj-0.3.5.dist-info/LICENSE
pdtj-0.3.5.dist-info/METADATA
pdtj-0.3.5.dist-info/WHEEL
pdtj-0.3.5.dist-info/entry_points.txt
pdtj-0.3.5.dist-info/top_level.txt
pdtj-0.3.5.dist-info/RECORD
