Metadata-Version: 2.1
Name: pdtj
Version: 0.3.5
Home-page: https://github.com/Joaopeuko/pdtj
Author: Joao Paulo Euko
License: MIT
Keywords: python,docstring,json
License-File: LICENSE
Requires-Dist: pyyaml (==6.0)
